gpx_editor/__init__.py
gpx_editor/__main__.py
gpx_editor/abbreviations.py
gpx_editor/cli.py
gpx_editor/editor.py
gpx_editor/gui.py
gpx_editor-1.0.0.dist-info/METADATA
gpx_editor-1.0.0.dist-info/WHEEL
gpx_editor-1.0.0.dist-info/entry_points.txt
gpx_editor-1.0.0.dist-info/RECORD
