Metadata-Version: 2.3
Name: gpx-editor
Version: 1.0.0
Summary: A tool for editing GPX files, specifically designed for moving and copying attributes between waypoints
Author: James Arnett
Requires-Python: >=3.8,<4.0
Classifier: Programming Language :: Python :: 3
Classifier: Programming Language :: Python :: 3.8
Classifier: Programming Language :: Python :: 3.9
Classifier: Programming Language :: Python :: 3.10
Classifier: Programming Language :: Python :: 3.11
Classifier: Programming Language :: Python :: 3.12
Classifier: Programming Language :: Python :: 3.13
Requires-Dist: xmltodict (>=0.13.0,<0.14.0)
